ISLP/__init__.py
ISLP/_version.py
ISLP/cluster.py
ISLP/pygam.py
ISLP/survival.py
ISLP/svm.py
ISLP/transforms.py
ISLP/bart/__init__.py
ISLP/bart/bart.py
ISLP/bart/likelihood.py
ISLP/bart/particle_tree.py
ISLP/bart/tree.py
ISLP/data/Auto.csv
ISLP/data/Auto.data
ISLP/data/Bikeshare.csv
ISLP/data/Boston.csv
ISLP/data/BrainCancer.csv
ISLP/data/Caravan.csv
ISLP/data/Carseats.csv
ISLP/data/College.csv
ISLP/data/Credit.csv
ISLP/data/Default.csv
ISLP/data/Fund.csv
ISLP/data/Hitters.csv
ISLP/data/Khan_xtest.csv
ISLP/data/Khan_xtrain.csv
ISLP/data/Khan_ytest.csv
ISLP/data/Khan_ytrain.csv
ISLP/data/NCI60data.npy
ISLP/data/NCI60labs.csv
ISLP/data/NYSE.csv
ISLP/data/OJ.csv
ISLP/data/Portfolio.csv
ISLP/data/Publication.csv
ISLP/data/Smarket.csv
ISLP/data/Wage.csv
ISLP/data/Weekly.csv
ISLP/models/__init__.py
ISLP/models/columns.py
ISLP/models/generic_selector.py
ISLP/models/model_spec.py
ISLP/models/sklearn_wrap.py
ISLP/models/strategy.py
ISLP/torch/__init__.py
ISLP/torch/imdb.py
ISLP/torch/lightning.py
ISLP-0.4.0.dist-info/METADATA
ISLP-0.4.0.dist-info/WHEEL
ISLP-0.4.0.dist-info/top_level.txt
ISLP-0.4.0.dist-info/RECORD
