Metadata-Version: 2.1
Name: ISLP
Version: 0.4.0
Summary: Library for ISLP labs
Author-email: Trevor Hastie <hastie@stanford.edu>, Gareth James <gareth@emory.edu>, Jonathan Taylor <jonathan.taylor@stanford.edu>, Rob Tibshirani <tibs@stanford.edu>, Daniela Witten <dwitten@uw.edu>
Maintainer-email: Jonathan Taylor <jonathan.taylor@stanford.edu>
License: Redistribution and use in source and binary forms, with or without
Project-URL: Homepage, https://github.com/intro-stat-learning/ISLP
Project-URL: Bug Reports, https://github.com/intro-stat-learning/ISLP/issues
Project-URL: Funding, https://donate.pypi.org
Project-URL: Say Thanks!, http://saythanks.io/to/example
Project-URL: Source, https://github.com/pypa/sampleproject/
Classifier: Development Status :: 3 - Alpha
Classifier: Environment :: Console
Classifier: Intended Audience :: Science/Research
Classifier: License :: OSI Approved :: BSD License
Classifier: Operating System :: OS Independent
Classifier: Programming Language :: Python
Classifier: Topic :: Scientific/Engineering
Requires-Python: >=3.9
Requires-Dist: numpy >=1.7.1
Requires-Dist: scipy >=0.9
Requires-Dist: pandas >=0.20
Requires-Dist: lxml
Requires-Dist: scikit-learn >=1.2
Requires-Dist: joblib
Requires-Dist: statsmodels >=0.13
Requires-Dist: lifelines
Requires-Dist: pygam
Requires-Dist: torch
Requires-Dist: pytorch-lightning
Requires-Dist: torchmetrics
Provides-Extra: doc
Requires-Dist: Sphinx >=3.0 ; extra == 'doc'
